quantom2d/__init__.py
quantom2d/core.py
quantom2d/entity.py
quantom2d/graphics.py
quantom2d/input.py
quantom2d/scene.py
quantom2d/time.py
quantom2d-0.1.0.dist-info/licenses/LICENSE
quantom2d-0.1.0.dist-info/METADATA
quantom2d-0.1.0.dist-info/WHEEL
quantom2d-0.1.0.dist-info/top_level.txt
quantom2d-0.1.0.dist-info/RECORD
