Metadata-Version: 2.4
Name: quantom2d
Version: 0.1.0
Summary: A lightweight 2D game library written in Python
Author-email: Lunar-Bytes <joar@strombackfamily.com>
Project-URL: Homepage, https://github.com/Lunar-Bytes/QuantomLibs
Project-URL: Issues, https://github.com/Lunar-Bytes/QuantomLibs/Issues
Keywords: game,2d,engine,pygame
Classifier: Programming Language :: Python :: 3
Classifier: License :: OSI Approved :: MIT License
Classifier: Operating System :: OS Independent
Requires-Python: >=3.8
License-File: LICENSE
Dynamic: license-file
